dsmc_tool/__init__.py
dsmc_tool/eval_results.py
dsmc_tool/evaluator.py
dsmc_tool/example.py
dsmc_tool/example_json_files/action_diversity.json
dsmc_tool/example_json_files/action_entropy.json
dsmc_tool/example_json_files/action_taken.json
dsmc_tool/example_json_files/action_threshold.json
dsmc_tool/example_json_files/action_variety.json
dsmc_tool/example_json_files/all_return.json
dsmc_tool/example_json_files/consecutive_same_action.json
dsmc_tool/example_json_files/custom_interval_return.json
dsmc_tool/example_json_files/early_termination.json
dsmc_tool/example_json_files/episode_length.json
dsmc_tool/example_json_files/goal_before_step_limit.json
dsmc_tool/example_json_files/goal_reaching_probability.json
dsmc_tool/example_json_files/interim_all_return.json
dsmc_tool/example_json_files/interim_return.json
dsmc_tool/example_json_files/normalized_return.json
dsmc_tool/example_json_files/path_efficiency.json
dsmc_tool/example_json_files/path_length_efficiency.json
dsmc_tool/example_json_files/return.json
dsmc_tool/example_json_files/return_threshold.json
dsmc_tool/example_json_files/reward_to_length_ratio.json
dsmc_tool/example_json_files/reward_variance.json
dsmc_tool/example_json_files/standard_return.json
dsmc_tool/example_json_files/state_coverage.json
dsmc_tool/example_json_files/state_transition_smoothness.json
dsmc_tool/property.py
dsmc_tool/statistics.py
dsmc_tool-0.2.1.dist-info/LICENSE
dsmc_tool-0.2.1.dist-info/METADATA
dsmc_tool-0.2.1.dist-info/WHEEL
dsmc_tool-0.2.1.dist-info/RECORD
